cici/__init__.py
cici/binary.py
cici/bitmap.py
cici/emotion.py
cici/imgmeta.py
cici/table.py
cici/tool.py
cici/util.py
cici/commands/__init__.py
cici/commands/_common.py
cici/commands/info.py
cici_toolkit-0.1.4.dist-info/LICENSE
cici_toolkit-0.1.4.dist-info/METADATA
cici_toolkit-0.1.4.dist-info/WHEEL
cici_toolkit-0.1.4.dist-info/entry_points.txt
cici_toolkit-0.1.4.dist-info/top_level.txt
cici_toolkit-0.1.4.dist-info/RECORD
