Metadata-Version: 2.1
Name: cici-toolkit
Version: 0.1.4
Summary: Cici: The Microsoft Comic Chat Toolkit
Home-page: https://gitlab.com/nanoNago/cici
Author: nago
Author-email: nago@malie.io
Maintainer: nago
Maintainer-email: nago@malie.io
Project-URL: Homepage, https://gitlab.com/nanoNago/cici
Project-URL: Documentation, https://gitlab.com/nanoNago/cici
Project-URL: Changelog, https://gitlab.com/nanoNago/cici
Project-URL: Issues, https://gitlab.com/nanoNago/cici/-/issues
Project-URL: Source, https://gitlab.com/nanoNago/cici
Classifier: Development Status :: 3 - Alpha
Classifier: Environment :: Console
Classifier: Intended Audience :: Developers
Classifier: Intended Audience :: End Users/Desktop
Classifier: License :: OSI Approved :: GNU Lesser General Public License v2 or later (LGPLv2+)
Classifier: Natural Language :: English
Classifier: Operating System :: OS Independent
Classifier: Programming Language :: Python :: 3 :: Only
Classifier: Programming Language :: Python :: 3.11
Classifier: Programming Language :: Python :: 3.12
Classifier: Programming Language :: Python :: 3.13
Classifier: Topic :: Communications :: Chat
Classifier: Topic :: Communications :: Chat :: Internet Relay Chat
Classifier: Topic :: File Formats
Classifier: Topic :: Multimedia :: Graphics
Classifier: Topic :: Multimedia :: Graphics :: Graphics Conversion
Classifier: Typing :: Typed
Requires-Python: >=3.11
License-File: LICENSE
Requires-Dist: Pillow>=9.0.0
Requires-Dist: chardet>=5.0.0
Requires-Dist: colorama>=0.4.6
Requires-Dist: termcolor>=2.4.0
Provides-Extra: devel
Requires-Dist: avocado-framework>=92.0; extra == "devel"
Requires-Dist: black>=23.0.0; extra == "devel"
Requires-Dist: coverage>=6.1.0; extra == "devel"
Requires-Dist: flake8>=5.0.4; extra == "devel"
Requires-Dist: isort>=5.1.2; extra == "devel"
Requires-Dist: mypy>=1.4.0; extra == "devel"
Requires-Dist: pylint>=2.17.3; extra == "devel"
Requires-Dist: tox>=3.18.0; extra == "devel"
Requires-Dist: types-Pillow; extra == "devel"
Requires-Dist: types-colorama; extra == "devel"
Requires-Dist: setuptools>=66.1.0; python_version >= "3.12" and extra == "devel"
